<?xml version="1.0" encoding="utf-8"?>
<Language xmlns:xsi="http://www.w3.org/2001/XMLSchema-instance" xmlns:xsd="http://www.w3.org/2001/XMLSchema">
  <Code>CS</Code>
  <Interface>
    <Record>
      <Key>TutoiralAirlocks</Key>
      <Value>Základní přechodové komory</Value>
    </Record>
    <Record>
      <Key>TutoiralAirlocksDescription</Key>
      <!--This is the description that appers in the menu-->
      <Value>Vítejte kadete. Chcete-li dokončit tuto fázi výstavby a natlakování základny, musíte postavit přechodovou komoru.</Value>
    </Record>
    <Record>
      <Key>TutoiralAtmosphericsSubTitle</Key>
      <Value>Praktický výcvik: Fáze I</Value>
    </Record>
    <Record>
      <Key>IntoTutoiralAtmosphericsDescription</Key>
      <!--This is the intro panel at the start of the tutorial-->
      <Value>Vítejte kadete. Chcete-li dokončit tuto fázi výstavby a natlakování základny, musíte postavit přechodovou komoru.</Value>
    </Record>
    <Record>
      <Key>4Narration1T</Key>
      <Value>Praktický výcvik: Fáze I</Value>
    </Record>
    <Record>
      <Key>4Narration1D</Key>
      <Value>Než začneme, vypadá to, že váš oblek utrpěl nějaké škody. Opravte ho lepicí páskou.</Value>
    </Record>
    <Record>
      <Key>4GetDucktape</Key>
      <Value>Vezměte z batohu lepicí páskou aktivní rukou.</Value>
    </Record>
    <Record>
      <Key>4UseDuctTape</Key>
      <Value>Oprava obleku.</Value>
    </Record>
    <Record>
      <Key>4PutCopperIngotInAutoLathe</Key>
      <Value>Přidejte zlatý ingot do autosoustruhu</Value>
    </Record>
    <Record>
      <Key>4PutGoldIngotInAutoLathe</Key>
      <Value>Přidejte zlatý ingot do autosoustruhu</Value>
    </Record>
    <Record>
      <Key>T4Deconstruct1</Key>
      <Value>Odstraňte zničený rám 1.</Value>
    </Record>
    <Record>
      <Key>T4Deconstruct2</Key>
      <Value>Odstraňte zničený rám 2.</Value>
    </Record>
    <Record>
      <Key>4BuildPDoor1Tutorial</Key>
      <Value>Postavte rám #1 do zvýrazněné oblasti.</Value>
    </Record>
    <Record>
      <Key>4BuildDoor2Tutorial</Key>
      <Value>Postavte rám #2 do zvýrazněné oblasti.</Value>
    </Record>
    <Record>
      <Key>OnStationpediaOpen</Key>
      <Value>Otevřete Stationpedii</Value>
    </Record>
    <Record>
      <Key>4BuildGasSensorTutorial</Key>
      <Value>Postavte rám na zvýrazněném místě.</Value>
    </Record>
    <Record>
      <Key>4BuildGasSensorTutorial</Key>
      <Value>Postavte rám na zvýrazněném místě.</Value>
    </Record>
    <Record>
      <Key>4FabricateAirlcokCircuit</Key>
      <Value>Tisk obvodové desky</Value>
    </Record>
    <Record>
      <Key>4FabricateDataDisk</Key>
      <Value>Tisk datového disku</Value>
    </Record>
    <Record>
      <Key>4FinsihConsole</Key>
      <Value>Dokončete konstrukci skleněných dveří.</Value>
    </Record>
    <Record>
      <Key>4ConsoleOn</Key>
      <Value>Zapněte tablet.</Value>
    </Record>
  </Interface>
</Language>
