<?xml version="1.0" encoding="utf-8"?>
<Language xmlns:xsi="http://www.w3.org/2001/XMLSchema-instance" xmlns:xsd="http://www.w3.org/2001/XMLSchema">
  <Code>CN</Code>
  <Interface>
    <Record>
      <Key>06BasicAtmospherics</Key>
      <Value>基础空气供应</Value>
    </Record>
    <Record>
      <Key>BasicAtmosphericsDescription</Key>
      <Value>在此章节中，你将学习如何给一个小型基地通入可呼吸空气。</Value>
    </Record>
    <Record>
      <Key>TheTabletAtmo</Key>
      <Value>追踪固态氧</Value>
    </Record>
    <Record>
      <Key>TheTabletAtmoDescription</Key>
      <Value>将跟踪器记忆卡放入 {THING:ItemTablet}。</Value>
    </Record>
    <Record>
      <Key>BasicAtmosphericsDescription</Key>
      <Value>在此章节中，你将学习如何给一个小型基地通入可呼吸空气。</Value>
    </Record>
    <Record>
      <Key>Oxyie-Gen</Key>
      <Value>收集固态氧</Value>
    </Record>
    <Record>
      <Key>Oxyie-GenTask1</Key>
      <Value>你需要开采大约100个固态氧来给基地加压。跟踪信标附近有两个矿床。滑动鼠标滚轮来切换正确的信标。</Value>
    </Record>
    <Record>
      <Key>Oxyie-GenDescription</Key>
      <Value>固态氧是一种冷冻的、可呼吸的气体，存在于大多数行星的小沉积物中。固态氧除非放在背包或采矿带中，否则会融化。
        
使用平板电脑，跑到固态氧信号点 。</Value>
    </Record>
    <Record>
      <Key>AtmoAirLock</Key>
      <Value>进入气闸</Value>
    </Record>
    <Record>
      <Key>AtmoAirLockDescription</Key>
      <Value>气闸是一种装置，能让人自由进出加压的基地的同时，将压力变化和基地空气损失降至最低。

目前，基地内部没有空气，因此气闸无法正常工作，它需要 100kpa 才能正常工作。但我们仍然可以通过取消气闸的气压平衡操作进入基地。请记住，如果您的基地有空气泄漏，千万不要运行气压平衡程序。</Value>
    </Record>
    <Record>
      <Key>AtmoAirLockTask1</Key>
      <Value>进入气闸舱然后点击控制台上的&quot;Cycle to Interior&quot; 按钮。等待外部门关闭，然后会出现一个标有&quot;Cancel Pressurize&quot;的新按钮。按下它然后内部门就会打开。
        </Value>
    </Record>
    <Record>
      <Key>AtmosAnalyser</Key>
      <Value>分析大气。</Value>
    </Record>
    <Record>
      <Key>AtmosAnalyserDescription</Key>
      <Value>大气分析仪芯片用于分析当前空气的组成成分、温度和压力信息。</Value>
    </Record>
    <Record>
      <Key>TheTabletTaskAtmo</Key>
      <Value>将 {THING:CartridgeAtmosAnalyser} 放入 {THING:ItemTablet}</Value>
    </Record>
    <Record>
      <Key>Creating_Atmo</Key>
      <Value>搞点空气。</Value>
    </Record>
    <Record>
      <Key>Creating_AtmoDescription</Key>
      <Value>创建可呼吸空气的最简单方法是先去挖点固体氧，然后把它扔进你的基地，让它自然融化。这将释放可呼吸的氧气到空间中，并增加气压。融化固体氧时要小心，因为一不小心可能会过压，对基地墙壁造成损坏。人类需要氧气含量至少到达20%，没有污染物或毒素的空气。空气中可以有少量的二氧化碳，但不建议超过10%。</Value>
    </Record>
    <Record>
      <Key>Creating_AtmoTask1</Key>
      <Value>启动 {THING:ItemTablet}。</Value>
    </Record>
    <Record>
      <Key>Creating_AtmoTask2</Key>
      <Value>将固态氧扔入房间，等待其融化。它将产生一个可呼吸的空气环境。让外部压力提高到60kPa。</Value>
    </Record>
    <Record>
      <Key>Creating_AtmoTask3</Key>
      <Value>一旦压力达到可接受的安全水平，打开头盔，呼吸这片属于你自己的新鲜空气吧。</Value>
    </Record>
  </Interface>
</Language>
