<?xml version="1.0" encoding="utf-8"?>
<Language xmlns:xsi="http://www.w3.org/2001/XMLSchema-instance" xmlns:xsd="http://www.w3.org/2001/XMLSchema">
  <Name>Polish</Name>
  <Code>PL</Code>
  <Font>font_russian</Font>
  <Interface>
    <Record>
      <Key>EscapeFromMarsTitle</Key>
      <Value>Ucieczka z Marsa [BETA]</Value>
    </Record>
    <Record>
      <Key>EscapeFromMarsDescription</Key>
      <Value>DLA TESTÓW: Tylko ze skromną ilością zasobów, musisz wykorzystać swój umysł oraz spryt i znaleźć sposób, aby przetrwać na Marsie.  Planując wszystko, to ostatecznie doprowadzi do wybudowania rakiety zdolnej opuścić atmosferę Marsa.</Value>
    </Record>
    <!-- Mission Stage: In Case of Emergency -->
    <Record>
      <Key>MarsTitleInCaseOfEmergency</Key>
      <Value>W razie wypadku...</Value>
    </Record>
    <Record>
      <Key>MarsDescInCaseOfEmergency</Key>
      <Value>Twój skafander jest uszkodzony i musisz znaleźć jakieś jedzenie.</Value>
    </Record>
    <Record>
      <Key>MarsTaskGetTape</Key>
      <Value>Znajdź {THING:ItemDuctTape}</Value>
    </Record>
    <Record>
      <Key>MarsTaskGetFood</Key>
      <Value>Znajdź {THING:ItemCerealBar}</Value>
    </Record>
    <Record>
      <Key>MarsTabletStage1</Key>
      <Value>PRZEWODNIK AWARYJNY</Value>
    </Record>
    <Record>
      <Key>MarsTabletStage1Page1</Key>
      <Value>STRONA 1 z 2\nNIE PANIKUJ.\n\nJeżeli to czytasz to przeżyłeś lub przeżyłaś ewakuację - gratulacje. Bez względu na Twoje otoczenie Twoim priorytetem jest zbadać swój stan zdrowia jak i też tych, którzy znajdują się w Twoim pobliżu. Dla pewności sprawdź stan swojego skafandra, ze względu na to, iż nie wiadomo w jakim środowisku będziesz się znajdować, a ochrona zapasów tlenu jest istotna.</Value>
    </Record>
    <Record>
      <Key>MarsTabletStage1Page2</Key>
      <Value>PAGE 2 z 2 \nJeśli znajdujesz się w pobliżu nienaruszonej kapsuły i dołączonej skrzyni z zaopatrzeniem to powinieneś/naś mieć jakieś niezbędne zapasy, które pomogą Ci w oczekiwaniu na ratunek. Jeżeli nie - poszukaj ocalałych.  Powinieneś/naś zaznaczyć lokalizację, lub zebrać, wszelkie zapasy, które będą najważniejsze dla Twojego przeżycia takie jak: jedzenie, baterie, użyteczne narzędzia, jak taśma klejąca i przenośne urządzenia przetrwania. \n</Value>
    </Record>
    <!-- Mission Stage: Aquire Raw Materials -->
    <Record>
      <Key>MarsTitleRawMaterials</Key>
      <Value>Błagaj, ryj i kradnij</Value>
    </Record>
    <Record>
      <Key>MarsTabletStage2</Key>
      <Value>SUROWCE</Value>
    </Record>
    <Record>
      <Key>MarsDescRawMaterials</Key>
      <Value>Znajdź sposób na wyprodukowanie podstawowych materiałów, których potrzebujesz do produkcji.</Value>
    </Record>
    <Record>
      <Key>MarsTaskGetIronIngots</Key>
      <Value>Weź {THING:ItemIronIngot}</Value>
    </Record>
    <Record>
      <Key>MarsTaskGetCopperIngots</Key>
      <Value>Weź {THING:ItemCopperIngot}</Value>
    </Record>
    <Record>
      <Key>MarsTaskGetGoldIngots</Key>
      <Value>Weź {THING:ItemGoldIngot}</Value>
    </Record>
    <!-- Mission Stage: Setup Manufacturing -->
    <Record>
      <Key>MarsTabletStage3</Key>
      <Value>PRODUKCYJNE 101</Value>
    </Record>
    <Record>
      <Key>MarsDescSetupManufacturing</Key>
      <Value>Aby wytworzyć wszystko, czego nam trzeba, powinniśmy zacząć od {THING:ItemKitHydraulicPipeBender} oraz {THING:ItemKitElectronicsPrinter}.</Value>
    </Record>
    <Record>
      <Key>MarsTaskManufactureHPB</Key>
      <Value>Wytwórz {THING:ItemKitHydraulicPipeBender}</Value>
    </Record>
    <Record>
      <Key>MarsTaskManufactureEP</Key>
      <Value>Wytwórz {THING:ItemKitElectronicsPrinter}</Value>
    </Record>
    <!-- Mission Stage: Food Supply -->
    <Record>
      <Key>MarsTitleFoodSupply</Key>
      <Value>Stabilne Źródło Pożywienia</Value>
    </Record>
    <Record>
      <Key>MarsTabletStage4</Key>
      <Value>PORADNIK DO OGRODNICTWA</Value>
    </Record>
    <Record>
      <Key>MarsDescFoodSupply</Key>
      <Value>Nie wiemy jak długo będziesz musiał tutaj przetrwać.  Powinniśmy przygotować odnawialne źródło jedzenia, na wszelki wypadek.</Value>
    </Record>
    <Record>
      <Key>MarsTaskPrepareAtmos</Key>
      <Value>Stwórz szczelne pomieszczenie z atmosferą zdolną do wzrostu Ziemniaków.</Value>
    </Record>
    <Record>
      <Key>MarsTaskGrowPotato</Key>
      <Value>Wyhoduj {THING:ItemPotato}.</Value>
    </Record>
    <!-- Mission Stage: Spawn Mothership & Engine -->
    <Record>
      <Key>MarsTitleCreateRocket</Key>
      <Value>Tworzenie Statku-Matki</Value>
    </Record>
    <Record>
      <Key>MarsTitleLaunchRocket</Key>
      <Value>Uruchamianie Statku-Matki</Value>
    </Record>
  </Interface>
</Language>
