<?xml version="1.0" encoding="utf-8"?>
<Language xmlns:xsi="http://www.w3.org/2001/XMLSchema-instance" xmlns:xsd="http://www.w3.org/2001/XMLSchema">
  <Code>KO</Code>
  <Interface>
    <Record>
      <Key>PortableHydroponicsTask1</Key>
      <Value>{THING:ItemTablet} 들기</Value>
    </Record>
    <Record>
      <Key>PortableHydroponicsTask2</Key>
      <Value>{THING:ItemTablet} 들기</Value>
    </Record>
    <Record>
      <Key>PortableHydroponicsTask3</Key>
      <Value>{THING:ItemTablet} 켜기</Value>
    </Record>
    <Record>
      <Key>PotatosInSpaceDescription</Key>
      <Value>{THING:ItemEvaSuit}슬롯 창 열기</Value>
    </Record>
    <Record>
      <Key>PotatosInSpaceTask2</Key>
      <Value>{THING:ItemTablet} 내려놓기</Value>
    </Record>
    <Record>
      <Key>FixedHydroponicsTask1</Key>
      <Value>{THING:ItemTablet} 들기</Value>
    </Record>
    <Record>
      <Key>FixedHydroponicsTask2</Key>
      <Value>{THING:ItemToolBelt}를 {SLOT:Belt}슬롯에 차기</Value>
    </Record>
    <Record>
      <Key>TankConnectorsWhatAreTheyTask1</Key>
      <Value>{THING:ItemTablet} 들기</Value>
    </Record>
    <Record>
      <Key>TankConnectorsWhatAreTheyTask2</Key>
      <Value>{THING:ItemToolBelt}를 {SLOT:Belt}슬롯에 차기</Value>
    </Record>
    <Record>
      <Key>WaterTanksAndWrenches1</Key>
      <Value>{THING:ItemToolBelt}를 {SLOT:Belt}슬롯에 차기</Value>
    </Record>
    <Record>
      <Key>WaterNetworksTask1</Key>
      <Value>{THING:ItemTablet} 들기</Value>
    </Record>
    <Record>
      <Key>WaterNetworksTask2</Key>
      <Value>{THING:ItemToolBelt}를 {SLOT:Belt}슬롯에 차기</Value>
    </Record>
    <Record>
      <Key>KeepingItTidyTask1</Key>
      <Value>{THING:ItemTablet} 들기</Value>
    </Record>
    <Record>
      <Key>KeepingItTidyTask2</Key>
      <Value>{THING:ItemToolBelt}를 {SLOT:Belt}슬롯에 차기</Value>
    </Record>
    <Record>
      <Key>AutomatedHydroponicsTask1</Key>
      <Value>{THING:ItemTablet} 켜기</Value>
    </Record>
    <Record>
      <Key>AutomatedHydroponicsTask2</Key>
      <Value>{THING:ItemTablet} 들기</Value>
    </Record>
    <Record>
      <Key>AutomatedHydroponicsTask3</Key>
      <Value>{THING:ItemTablet}에 {THING:ItemBatteryCellLarge} 끼우기</Value>
    </Record>
    <Record>
      <Key>HonestWorkTask2</Key>
      <Value>{THING:ItemTablet} 들기</Value>
    </Record>
  </Interface>
</Language>
