<?xml version="1.0" encoding="utf-8"?>
<Language xmlns:xsi="http://www.w3.org/2001/XMLSchema-instance" xmlns:xsd="http://www.w3.org/2001/XMLSchema">
  <Code>DA</Code>
  <Interface>
    <Record>
      <Key>ConsoleManualControlSetupTask1</Key>
      <Value>Tag {THING:ItemSpaceHelmet}en på</Value>
    </Record>
    <Record>
      <Key>ConsoleManualControlSetupTask2</Key>
      <Value>Tag {THING:ItemSpaceHelmet}en på</Value>
    </Record>
    <Record>
      <Key>ConsoleManualControlSetupTask3</Key>
      <Value>Tag {THING:ItemSpaceHelmet}en på</Value>
    </Record>
    <Record>
      <Key>ConsoleManualControlSetupTask4</Key>
      <Value>Tag {THING:ItemSpaceHelmet}en på</Value>
    </Record>
    <Record>
      <Key>ConsoleManualControlSetupTask5</Key>
      <Value>Tag {THING:ItemSpaceHelmet}en på</Value>
    </Record>
    <Record>
      <Key>PickUpDaylightSensor</Key>
      <Value>Tag {THING:ItemSpaceHelmet}en på</Value>
    </Record>
    <Record>
      <Key>SetupLogicWritter1</Key>
      <Value>Tag {THING:ItemSpaceHelmet}en på</Value>
    </Record>
    <Record>
      <Key>VerticalBatchWritterSetup4</Key>
      <Value>Tag {THING:ItemSpaceHelmet}en på</Value>
    </Record>
    <Record>
      <Key>PickUpLogicInputOutput</Key>
      <Value>Tag {THING:ItemEvaSuit}en på</Value>
    </Record>
    <Record>
      <Key>HorizontalBatchWritterSetup4</Key>
      <Value>Tag {THING:ItemSpaceHelmet}en på</Value>
    </Record>
  </Interface>
</Language>
