<?xml version="1.0" encoding="utf-8"?>
<Language xmlns:xsi="http://www.w3.org/2001/XMLSchema-instance" xmlns:xsd="http://www.w3.org/2001/XMLSchema">
  <Code>DE</Code>
  <Interface>
    <Record>
      <Key>ConsoleManuallControl1</Key>
      <Value>{THING:ItemAreaPowerControl} im hervorgehobenen Bereich platzieren.</Value>
    </Record>
    <Record>
      <Key>ConsoleManuallControl2</Key>
      <Value>{THING:ItemAreaPowerControl} im hervorgehobenen Bereich platzieren.</Value>
    </Record>
    <Record>
      <Key>ConsoleManualControlSetupTask1</Key>
      <Value>Mit dem {THING:ItemMiningDrill} etwas {THING:ItemCoalOre} abbauen</Value>
    </Record>
    <Record>
      <Key>ConsoleManualControlSetupTask2</Key>
      <Value>Zwei {THING:ItemPlasticSheets} herstellen.</Value>
    </Record>
    <Record>
      <Key>ConsoleManualControlSetupTask3</Key>
      <Value>{THING:StructureAreaPowerControl} mit einer {THING:ItemBatteryCellLarge} ausrüsten.</Value>
    </Record>
    <Record>
      <Key>ConsoleManualControlSetupTask4</Key>
      <Value>Den {THING:StructureArcFurnace} einschalten.</Value>
    </Record>
    <Record>
      <Key>ConsoleManualControlSetupTask5</Key>
      <Value>{THING:StructureAreaPowerControl} mit einer {THING:ItemBatteryCellLarge} ausrüsten.</Value>
    </Record>
    <Record>
      <Key>PickUpDaylightSensor</Key>
      <Value>{THING:ItemCopperIngot} aus der orangenen Kiste nehmen.</Value>
    </Record>
    <Record>
      <Key>DaylightSensor1</Key>
      <Value>{THING:ItemAreaPowerControl} im hervorgehobenen Bereich platzieren.</Value>
    </Record>
    <Record>
      <Key>PickUpMemory</Key>
      <Value>{THING:ItemSiliconIngot} aus der orangenen Kiste nehmen.</Value>
    </Record>
    <Record>
      <Key>StructureLogicMemory</Key>
      <Value>{THING:ItemAreaPowerControl} im hervorgehobenen Bereich platzieren.</Value>
    </Record>
    <Record>
      <Key>SetupLogicWritter1</Key>
      <Value>Den {THING:StructureArcFurnace} einschalten.</Value>
    </Record>
    <Record>
      <Key>SetupLogicWritter2</Key>
      <Value>{THING:StructureHydraulicPipeBender} fertig stellen.</Value>
    </Record>
    <Record>
      <Key>PickUpLogicProcessor</Key>
      <Value>{THING:ItemSiliconIngot} aus der orangenen Kiste nehmen.</Value>
    </Record>
    <Record>
      <Key>LogicWriter1</Key>
      <Value>{THING:ItemAreaPowerControl} im hervorgehobenen Bereich platzieren.</Value>
    </Record>
    <Record>
      <Key>LogicReader1</Key>
      <Value>{THING:ItemAreaPowerControl} im hervorgehobenen Bereich platzieren.</Value>
    </Record>
    <Record>
      <Key>PlaceLogicMath</Key>
      <Value>{THING:ItemAreaPowerControl} im hervorgehobenen Bereich platzieren.</Value>
    </Record>
    <Record>
      <Key>PlaceLogicMath1</Key>
      <Value>{THING:ItemAreaPowerControl} im hervorgehobenen Bereich platzieren.</Value>
    </Record>
    <Record>
      <Key>VerticalBatchWritterSetup4</Key>
      <Value>Die {THING:StructureAutolathe} einschalten.</Value>
    </Record>
    <Record>
      <Key>PickUpLogicInputOutput</Key>
      <Value>{THING:ItemSiliconIngot} aus der orangenen Kiste nehmen.</Value>
    </Record>
    <Record>
      <Key>BatchWriter1</Key>
      <Value>{THING:ItemAreaPowerControl} im hervorgehobenen Bereich platzieren.</Value>
    </Record>
    <Record>
      <Key>PlaceLogicMath2</Key>
      <Value>{THING:ItemAreaPowerControl} im hervorgehobenen Bereich platzieren.</Value>
    </Record>
    <Record>
      <Key>PlaceLogicMath3</Key>
      <Value>{THING:ItemAreaPowerControl} im hervorgehobenen Bereich platzieren.</Value>
    </Record>
    <Record>
      <Key>BatchWriter2</Key>
      <Value>{THING:ItemAreaPowerControl} im hervorgehobenen Bereich platzieren.</Value>
    </Record>
    <Record>
      <Key>HorizontalBatchWritterSetup4</Key>
      <Value>Die {THING:StructureAutolathe} einschalten.</Value>
    </Record>
    <Record>
      <Key>LogicSelect1</Key>
      <Value>{THING:ItemAreaPowerControl} im hervorgehobenen Bereich platzieren.</Value>
    </Record>
    <Record>
      <Key>LogicSelect2</Key>
      <Value>{THING:ItemAreaPowerControl} im hervorgehobenen Bereich platzieren.</Value>
    </Record>
  </Interface>
</Language>
