<?xml version="1.0" encoding="utf-8"?>
<Language xmlns:xsi="http://www.w3.org/2001/XMLSchema-instance" xmlns:xsd="http://www.w3.org/2001/XMLSchema">
  <Code>PT</Code>
  <Interface>
    <Record>
      <Key>TheNewBeginningTitle</Key>
      <Value>O Novo Começo [BETA]</Value>
    </Record>
    <Record>
      <Key>TheNewBeginningDescription</Key>
      <Value>Vamos aprender o básico, e aprender como ser o melhor Stationeer que possas ser!</Value>
    </Record>
    <!-- start the tutorial -->
    <Record>
      <Key>TutorialTheBeginningTitle</Key>
      <Value>O Começo</Value>
    </Record>
  </Interface>
</Language>
